numer/__deps__.py
numer/__init__.py
numer/betLam.py
numer/depLam.py
numer/getLam.py
numer/iniLam.py
numer/modLas.py
numer/shfLam.py
muti.numer-0.0.14.dist-info/LICENSE
muti.numer-0.0.14.dist-info/METADATA
muti.numer-0.0.14.dist-info/WHEEL
muti.numer-0.0.14.dist-info/top_level.txt
muti.numer-0.0.14.dist-info/RECORD
