Metadata-Version: 2.1
Name: muti.numer
Version: 0.0.14
Summary: utils for math-numer
Home-page: https://github.com/E-C-Ares/
Author: E.C.Ares
Author-email: E.C.Ares@outlook.com
License: MIT DIVIƷON
Classifier: Programming Language :: Python :: 3
Classifier: License :: OSI Approved :: MIT License
Classifier: Operating System :: OS Independent
License-File: LICENSE
